lumpy_log/__init__.py
lumpy_log/__main__.py
lumpy_log/changelump.py
lumpy_log/cli.py
lumpy_log/config.py
lumpy_log/core.py
lumpy_log/languages.py
lumpy_log/languages.yml
lumpy_log/list1.py
lumpy_log/md_to_docx.py
lumpy_log/tap_parser.py
lumpy_log/test_processor.py
lumpy_log/utils.py
lumpy_log/templates/commit_entry.md
lumpy_log/templates/journal-entry.md
lumpy_log/templates/modified_files.md
lumpy_log/templates/obsidian_index.md
lumpy_log/templates/test_results.md
lumpy_log-0.1.8.dist-info/licenses/LICENSE
lumpy_log-0.1.8.dist-info/METADATA
lumpy_log-0.1.8.dist-info/WHEEL
lumpy_log-0.1.8.dist-info/entry_points.txt
lumpy_log-0.1.8.dist-info/top_level.txt
lumpy_log-0.1.8.dist-info/RECORD
