Metadata-Version: 2.4
Name: lumpy-log
Version: 0.1.8
Summary: Make git logs easier for use in scenarios when communicating the progress of a project to non-experts
Author: UTC Sheffield
License: MIT
Project-URL: Homepage, https://github.com/UTCSheffield/lumpy_log
Project-URL: Repository, https://github.com/UTCSheffield/lumpy_log
Keywords: git,log,visualization,changelog
Classifier: Development Status :: 3 - Alpha
Classifier: Intended Audience :: Developers
Classifier: Topic :: Software Development :: Version Control :: Git
Classifier: License :: OSI Approved :: MIT License
Classifier: Programming Language :: Python :: 3
Classifier: Programming Language :: Python :: 3.7
Classifier: Programming Language :: Python :: 3.8
Classifier: Programming Language :: Python :: 3.9
Classifier: Programming Language :: Python :: 3.10
Classifier: Programming Language :: Python :: 3.11
Requires-Python: >=3.7
License-File: LICENSE
Requires-Dist: pydriller>=2.0
Requires-Dist: pygments
Requires-Dist: jinja2
Requires-Dist: pyyaml
Requires-Dist: pathspec
Requires-Dist: mdformat
Requires-Dist: python-docx>=0.8.11
Requires-Dist: Pillow>=9.0
Requires-Dist: Pygments>=2.14
Requires-Dist: requests>=2.31
Provides-Extra: docx-playwright
Requires-Dist: playwright>=1.40; extra == "docx-playwright"
Provides-Extra: all
Requires-Dist: playwright>=1.40; extra == "all"
Dynamic: license-file
